NBEATS/NBEATS.py
NBEATS/__init__.py
NBEATS/model.py
NBEATS-1.3.11.dist-info/METADATA
NBEATS-1.3.11.dist-info/WHEEL
NBEATS-1.3.11.dist-info/top_level.txt
NBEATS-1.3.11.dist-info/RECORD
