Metadata-Version: 2.1
Name: NBEATS
Version: 1.3.11
Summary: This library uses nbeats-pytorch as base and accomplishes univariate time series forecasting using N-BEATS.
Home-page: https://github.com/Y9008/NBEATS
Author: Yazdan Khan
Author-email: yazdan0891@gmail.com
License: MIT
Keywords: nbeats,timeseries,forecast,neural beats,univariate timeseries forecast ,timeseries forecast,univariate timeseries forecast
Platform: UNKNOWN
Classifier: Development Status :: 5 - Production/Stable
Classifier: Topic :: Software Development :: Build Tools
Classifier: License :: OSI Approved :: MIT License
Requires-Python: >=3.6
Requires-Dist: nbeats-pytorch
